README.rst
setup.py
perth/__init__.py
perth/perth.py
perth.egg-info/PKG-INFO
perth.egg-info/SOURCES.txt
perth.egg-info/dependency_links.txt
perth.egg-info/top_level.txt