Metadata-Version: 1.1
Name: perth
Version: 1.0.0
Summary: UNKNOWN
Home-page: http://github.com/tomokinakamaru/perth
Author: Tomoki Nakamaru
Author-email: tomoki.nakamaru@gmail.com
License: MIT
Platform: any
Classifier: Development Status :: 4 - Beta
Classifier: Intended Audience :: Developers
Classifier: License :: OSI Approved :: MIT License
Classifier: Programming Language :: Python
Classifier: Topic :: Software Development :: Libraries :: Python Modules
